<?xml version="1.0" encoding="utf-8"?>
<operations>
  <operation>
    <deviceID>
    </deviceID>
    <userID>0000</userID>
    <sdatetimeSTR>26.10.2001 16:52:10</sdatetimeSTR>
    <edatetimeSTR>26.10.2001 16:52:11</edatetimeSTR>
  </operation>
  <operation>
    <deviceID>T2058</deviceID>
    <userID>3927</userID>
    <sdatetimeSTR>10.11.2023 8:52:49</sdatetimeSTR>
    <edatetimeSTR>10.11.2023 9:01:21</edatetimeSTR>
  </operation>
  <operation>
    <deviceID>T2058</deviceID>
    <userID>2692</userID>
    <sdatetimeSTR>10.11.2023 20:26:53</sdatetimeSTR>
    <edatetimeSTR>11.11.2023 8:33:37</edatetimeSTR>
  </operation>
  <operation>
    <deviceID>T2058</deviceID>
    <userID>0261</userID>
    <sdatetimeSTR>11.11.2023 18:06:46</sdatetimeSTR>
    <edatetimeSTR>11.11.2023 23:47:08</edatetimeSTR>
  </operation>
  <operation>
    <deviceID>T2058</deviceID>
    <userID>1499</userID>
    <sdatetimeSTR>12.11.2023 8:42:04</sdatetimeSTR>
    <edatetimeSTR>12.11.2023 20:37:10</edatetimeSTR>
  </operation>
  <operation>
    <deviceID>T2058</deviceID>
    <userID>3691</userID>
    <sdatetimeSTR>14.11.2023 20:39:25</sdatetimeSTR>
    <edatetimeSTR>15.11.2023 8:27:30</edatetimeSTR>
  </operation>
  <operation>
    <deviceID>T2058</deviceID>
    <userID>3992</userID>
    <sdatetimeSTR>16.11.2023 8:55:14</sdatetimeSTR>
    <edatetimeSTR>16.11.2023 21:20:13</edatetimeSTR>
  </operation>
  <operation>
    <deviceID>T2058</deviceID>
    <userID>0951</userID>
    <sdatetimeSTR>17.11.2023 15:13:18</sdatetimeSTR>
    <edatetimeSTR>18.11.2023 3:05:36</edatetimeSTR>
  </operation>
  <operation>
    <deviceID>T2058</deviceID>
    <userID>3691</userID>
    <sdatetimeSTR>18.11.2023 20:45:38</sdatetimeSTR>
    <edatetimeSTR>19.11.2023 8:30:56</edatetimeSTR>
  </operation>
  <operation>
    <deviceID>T2058</deviceID>
    <userID>0365</userID>
    <sdatetimeSTR>19.11.2023 14:13:50</sdatetimeSTR>
    <edatetimeSTR>19.11.2023 20:44:12</edatetimeSTR>
  </operation>
  <operation>
    <deviceID>T2058</deviceID>
    <userID>2954</userID>
    <sdatetimeSTR>20.11.2023 5:50:43</sdatetimeSTR>
    <edatetimeSTR>20.11.2023 8:24:50</edatetimeSTR>
  </operation>
  <operation>
    <deviceID>T2058</deviceID>
    <userID>1759</userID>
    <sdatetimeSTR>21.11.2023 4:06:51</sdatetimeSTR>
    <edatetimeSTR>21.11.2023 8:37:22</edatetimeSTR>
  </operation>
  <operation>
    <deviceID>T2058</deviceID>
    <userID>1090</userID>
    <sdatetimeSTR>23.11.2023 8:43:03</sdatetimeSTR>
    <edatetimeSTR>23.11.2023 8:43:09</edatetimeSTR>
  </operation>
  <operation>
    <deviceID>T2058</deviceID>
    <userID>1399</userID>
    <sdatetimeSTR>23.11.2023 8:43:17</sdatetimeSTR>
    <edatetimeSTR>23.11.2023 20:34:56</edatetimeSTR>
  </operation>
  <operation>
    <deviceID>T2058</deviceID>
    <userID>3645</userID>
    <sdatetimeSTR>24.11.2023 8:46:18</sdatetimeSTR>
    <edatetimeSTR>24.11.2023 19:09:07</edatetimeSTR>
  </operation>
  <operation>
    <deviceID>T2058</deviceID>
    <userID>2238</userID>
    <sdatetimeSTR>25.11.2023 8:46:47</sdatetimeSTR>
    <edatetimeSTR>25.11.2023 20:40:56</edatetimeSTR>
  </operation>
  <operation>
    <deviceID>T2058</deviceID>
    <userID>0815</userID>
    <sdatetimeSTR>26.11.2023 9:02:34</sdatetimeSTR>
    <edatetimeSTR>26.11.2023 13:48:49</edatetimeSTR>
  </operation>
  <operation>
    <deviceID>T2058</deviceID>
    <userID>1086</userID>
    <sdatetimeSTR>26.11.2023 17:32:28</sdatetimeSTR>
    <edatetimeSTR>26.11.2023 20:23:06</edatetimeSTR>
  </operation>
  <operation>
    <deviceID>T2058</deviceID>
    <userID>3538</userID>
    <sdatetimeSTR>27.11.2023 7:23:43</sdatetimeSTR>
    <edatetimeSTR>27.11.2023 8:14:42</edatetimeSTR>
  </operation>
  <operation>
    <deviceID>T2058</deviceID>
    <userID>0123</userID>
    <sdatetimeSTR>29.11.2023 5:13:26</sdatetimeSTR>
    <edatetimeSTR>29.11.2023 8:50:48</edatetimeSTR>
  </operation>
  <operation>
    <deviceID>T2058</deviceID>
    <userID>0869</userID>
    <sdatetimeSTR>01.12.2023 8:42:08</sdatetimeSTR>
    <edatetimeSTR>01.12.2023 22:22:43</edatetimeSTR>
  </operation>
  <operation>
    <deviceID>T2058</deviceID>
    <userID>2599</userID>
    <sdatetimeSTR>02.12.2023 20:37:09</sdatetimeSTR>
    <edatetimeSTR>03.12.2023 8:16:49</edatetimeSTR>
  </operation>
  <operation>
    <deviceID>T2058</deviceID>
    <userID>3130</userID>
    <sdatetimeSTR>03.12.2023 18:32:44</sdatetimeSTR>
    <edatetimeSTR>04.12.2023 8:21:47</edatetimeSTR>
  </operation>
  <operation>
    <deviceID>T2058</deviceID>
    <userID>3538</userID>
    <sdatetimeSTR>05.12.2023 1:14:15</sdatetimeSTR>
    <edatetimeSTR>05.12.2023 8:24:04</edatetimeSTR>
  </operation>
  <operation>
    <deviceID>T2058</deviceID>
    <userID>2251</userID>
    <sdatetimeSTR>06.12.2023 20:40:09</sdatetimeSTR>
    <edatetimeSTR>07.12.2023 5:18:08</edatetimeSTR>
  </operation>
  <operation>
    <deviceID>T2058</deviceID>
    <userID>1531</userID>
    <sdatetimeSTR>09.12.2023 15:06:10</sdatetimeSTR>
    <edatetimeSTR>09.12.2023 20:37:15</edatetimeSTR>
  </operation>
  <operation>
    <deviceID>T2058</deviceID>
    <userID>0815</userID>
    <sdatetimeSTR>11.12.2023 3:40:47</sdatetimeSTR>
    <edatetimeSTR>11.12.2023 8:43:18</edatetimeSTR>
  </operation>
  <operation>
    <deviceID>T2058</deviceID>
    <userID>3645</userID>
    <sdatetimeSTR>11.12.2023 19:09:26</sdatetimeSTR>
    <edatetimeSTR>11.12.2023 21:06:23</edatetimeSTR>
  </operation>
  <operation>
    <deviceID>T2058</deviceID>
    <userID>1499</userID>
    <sdatetimeSTR>12.12.2023 20:55:17</sdatetimeSTR>
    <edatetimeSTR>13.12.2023 8:08:14</edatetimeSTR>
  </operation>
  <operation>
    <deviceID>T2058</deviceID>
    <userID>0815</userID>
    <sdatetimeSTR>15.12.2023 5:24:20</sdatetimeSTR>
    <edatetimeSTR>15.12.2023 8:37:47</edatetimeSTR>
  </operation>
  <operation>
    <deviceID>T2058</deviceID>
    <userID>2251</userID>
    <sdatetimeSTR>17.12.2023 8:34:24</sdatetimeSTR>
    <edatetimeSTR>17.12.2023 13:16:44</edatetimeSTR>
  </operation>
  <operation>
    <deviceID>T2058</deviceID>
    <userID>2048</userID>
    <sdatetimeSTR>18.12.2023 20:40:21</sdatetimeSTR>
    <edatetimeSTR>19.12.2023 6:18:35</edatetimeSTR>
  </operation>
  <operation>
    <deviceID>T2058</deviceID>
    <userID>1016</userID>
    <sdatetimeSTR>21.12.2023 8:44:13</sdatetimeSTR>
    <edatetimeSTR>21.12.2023 21:14:06</edatetimeSTR>
  </operation>
  <operation>
    <deviceID>T2058</deviceID>
    <userID>0365</userID>
    <sdatetimeSTR>22.12.2023 20:38:53</sdatetimeSTR>
    <edatetimeSTR>23.12.2023 8:45:44</edatetimeSTR>
  </operation>
  <operation>
    <deviceID>T2058</deviceID>
    <userID>2543</userID>
    <sdatetimeSTR>25.12.2023 8:46:46</sdatetimeSTR>
    <edatetimeSTR>25.12.2023 19:51:19</edatetimeSTR>
  </operation>
  <operation>
    <deviceID>T2058</deviceID>
    <userID>0123</userID>
    <sdatetimeSTR>26.12.2023 11:58:34</sdatetimeSTR>
    <edatetimeSTR>26.12.2023 20:05:24</edatetimeSTR>
  </operation>
  <operation>
    <deviceID>T2058</deviceID>
    <userID>3944</userID>
    <sdatetimeSTR>27.12.2023 8:47:49</sdatetimeSTR>
    <edatetimeSTR>27.12.2023 21:55:33</edatetimeSTR>
  </operation>
  <operation>
    <deviceID>T2058</deviceID>
    <userID>3669</userID>
    <sdatetimeSTR>28.12.2023 4:26:04</sdatetimeSTR>
    <edatetimeSTR>28.12.2023 8:09:22</edatetimeSTR>
  </operation>
  <operation>
    <deviceID>T2058</deviceID>
    <userID>1531</userID>
    <sdatetimeSTR>28.12.2023 15:44:48</sdatetimeSTR>
    <edatetimeSTR>28.12.2023 21:13:27</edatetimeSTR>
  </operation>
  <operation>
    <deviceID>T2058</deviceID>
    <userID>3640</userID>
    <sdatetimeSTR>29.12.2023 8:55:08</sdatetimeSTR>
    <edatetimeSTR>29.12.2023 16:14:52</edatetimeSTR>
  </operation>
  <operation>
    <deviceID>T2058</deviceID>
    <userID>1309</userID>
    <sdatetimeSTR>29.12.2023 18:05:38</sdatetimeSTR>
    <edatetimeSTR>29.12.2023 23:14:16</edatetimeSTR>
  </operation>
  <operation>
    <deviceID>T2058</deviceID>
    <userID>0045</userID>
    <sdatetimeSTR>06.01.2024 15:05:10</sdatetimeSTR>
    <edatetimeSTR>06.01.2024 20:53:11</edatetimeSTR>
  </operation>
  <operation>
    <deviceID>T2058</deviceID>
    <userID>3669</userID>
    <sdatetimeSTR>08.01.2024 9:09:21</sdatetimeSTR>
    <edatetimeSTR>08.01.2024 21:12:54</edatetimeSTR>
  </operation>
  <operation>
    <deviceID>T2058</deviceID>
    <userID>1936</userID>
    <sdatetimeSTR>10.01.2024 9:16:23</sdatetimeSTR>
    <edatetimeSTR>10.01.2024 18:08:01</edatetimeSTR>
  </operation>
  <operation>
    <deviceID>T2058</deviceID>
    <userID>0123</userID>
    <sdatetimeSTR>12.01.2024 23:20:25</sdatetimeSTR>
    <edatetimeSTR>13.01.2024 8:09:31</edatetimeSTR>
  </operation>
  <operation>
    <deviceID>T2058</deviceID>
    <userID>0951</userID>
    <sdatetimeSTR>13.01.2024 20:45:30</sdatetimeSTR>
    <edatetimeSTR>14.01.2024 7:21:50</edatetimeSTR>
  </operation>
  <operation>
    <deviceID>T2058</deviceID>
    <userID>1383</userID>
    <sdatetimeSTR>15.01.2024 4:16:00</sdatetimeSTR>
    <edatetimeSTR>15.01.2024 8:28:27</edatetimeSTR>
  </operation>
  <operation>
    <deviceID>T2058</deviceID>
    <userID>2127</userID>
    <sdatetimeSTR>18.01.2024 8:34:52</sdatetimeSTR>
    <edatetimeSTR>18.01.2024 20:34:39</edatetimeSTR>
  </operation>
  <operation>
    <deviceID>T2058</deviceID>
    <userID>2051</userID>
    <sdatetimeSTR>20.01.2024 21:15:43</sdatetimeSTR>
    <edatetimeSTR>21.01.2024 5:09:24</edatetimeSTR>
  </operation>
  <operation>
    <deviceID>T2058</deviceID>
    <userID>1595</userID>
    <sdatetimeSTR>21.01.2024 19:29:41</sdatetimeSTR>
    <edatetimeSTR>22.01.2024 8:22:43</edatetimeSTR>
  </operation>
  <operation>
    <deviceID>T2058</deviceID>
    <userID>3136</userID>
    <sdatetimeSTR>23.01.2024 21:49:49</sdatetimeSTR>
    <edatetimeSTR>24.01.2024 8:39:51</edatetimeSTR>
  </operation>
  <operation>
    <deviceID>T2058</deviceID>
    <userID>2599</userID>
    <sdatetimeSTR>26.01.2024 8:49:31</sdatetimeSTR>
    <edatetimeSTR>26.01.2024 20:36:35</edatetimeSTR>
  </operation>
  <operation>
    <deviceID>T2058</deviceID>
    <userID>3130</userID>
    <sdatetimeSTR>28.01.2024 16:02:22</sdatetimeSTR>
    <edatetimeSTR>29.01.2024 4:51:12</edatetimeSTR>
  </operation>
  <operation>
    <deviceID>T2058</deviceID>
    <userID>1465</userID>
    <sdatetimeSTR>30.01.2024 20:28:23</sdatetimeSTR>
    <edatetimeSTR>31.01.2024 3:24:00</edatetimeSTR>
  </operation>
  <operation>
    <deviceID>T2058</deviceID>
    <userID>1102</userID>
    <sdatetimeSTR>31.01.2024 17:50:05</sdatetimeSTR>
    <edatetimeSTR>31.01.2024 20:53:26</edatetimeSTR>
  </operation>
  <operation>
    <deviceID>T2058</deviceID>
    <userID>3664</userID>
    <sdatetimeSTR>01.02.2024 9:05:53</sdatetimeSTR>
    <edatetimeSTR>01.02.2024 20:51:11</edatetimeSTR>
  </operation>
  <operation>
    <deviceID>T2058</deviceID>
    <userID>3976</userID>
    <sdatetimeSTR>04.02.2024 20:36:55</sdatetimeSTR>
    <edatetimeSTR>05.02.2024 5:11:56</edatetimeSTR>
  </operation>
  <operation>
    <deviceID>T2058</deviceID>
    <userID>1473</userID>
    <sdatetimeSTR>07.02.2024 8:44:24</sdatetimeSTR>
    <edatetimeSTR>07.02.2024 17:19:44</edatetimeSTR>
  </operation>
  <operation>
    <deviceID>T2058</deviceID>
    <userID>0261</userID>
    <sdatetimeSTR>11.02.2024 8:29:48</sdatetimeSTR>
    <edatetimeSTR>11.02.2024 17:22:09</edatetimeSTR>
  </operation>
  <operation>
    <deviceID>T2058</deviceID>
    <userID>3255</userID>
    <sdatetimeSTR>15.02.2024 15:38:33</sdatetimeSTR>
    <edatetimeSTR>16.02.2024 2:21:08</edatetimeSTR>
  </operation>
  <operation>
    <deviceID>T2058</deviceID>
    <userID>1452</userID>
    <sdatetimeSTR>16.02.2024 20:39:01</sdatetimeSTR>
    <edatetimeSTR>17.02.2024 8:26:11</edatetimeSTR>
  </operation>
  <operation>
    <deviceID>T2058</deviceID>
    <userID>3247</userID>
    <sdatetimeSTR>19.02.2024 8:40:20</sdatetimeSTR>
    <edatetimeSTR>19.02.2024 17:13:47</edatetimeSTR>
  </operation>
  <operation>
    <deviceID>T2058</deviceID>
    <userID>3992</userID>
    <sdatetimeSTR>20.02.2024 8:27:20</sdatetimeSTR>
    <edatetimeSTR>20.02.2024 20:48:01</edatetimeSTR>
  </operation>
  <operation>
    <deviceID>T2058</deviceID>
    <userID>3103</userID>
    <sdatetimeSTR>23.02.2024 8:24:35</sdatetimeSTR>
    <edatetimeSTR>23.02.2024 20:52:29</edatetimeSTR>
  </operation>
  <operation>
    <deviceID>T2058</deviceID>
    <userID>0500</userID>
    <sdatetimeSTR>24.02.2024 9:27:14</sdatetimeSTR>
    <edatetimeSTR>25.02.2024 8:31:37</edatetimeSTR>
  </operation>
  <operation>
    <deviceID>T2058</deviceID>
    <userID>1287</userID>
    <sdatetimeSTR>27.02.2024 8:18:31</sdatetimeSTR>
    <edatetimeSTR>27.02.2024 21:11:09</edatetimeSTR>
  </operation>
  <operation>
    <deviceID>T2058</deviceID>
    <userID>2127</userID>
    <sdatetimeSTR>28.02.2024 20:14:38</sdatetimeSTR>
    <edatetimeSTR>29.02.2024 8:29:11</edatetimeSTR>
  </operation>
  <operation>
    <deviceID>T2058</deviceID>
    <userID>2083</userID>
    <sdatetimeSTR>29.02.2024 21:28:24</sdatetimeSTR>
    <edatetimeSTR>01.03.2024 8:34:34</edatetimeSTR>
  </operation>
  <operation>
    <deviceID>T2058</deviceID>
    <userID>3282</userID>
    <sdatetimeSTR>02.03.2024 8:22:27</sdatetimeSTR>
    <edatetimeSTR>02.03.2024 20:48:45</edatetimeSTR>
  </operation>
  <operation>
    <deviceID>T2058</deviceID>
    <userID>3570</userID>
    <sdatetimeSTR>03.03.2024 20:25:32</sdatetimeSTR>
    <edatetimeSTR>04.03.2024 8:47:32</edatetimeSTR>
  </operation>
  <operation>
    <deviceID>T2058</deviceID>
    <userID>0815</userID>
    <sdatetimeSTR>06.03.2024 8:35:13</sdatetimeSTR>
    <edatetimeSTR>06.03.2024 20:42:53</edatetimeSTR>
  </operation>
  <operation>
    <deviceID>T2058</deviceID>
    <userID>1452</userID>
    <sdatetimeSTR>07.03.2024 20:32:00</sdatetimeSTR>
    <edatetimeSTR>08.03.2024 8:58:32</edatetimeSTR>
  </operation>
  <operation>
    <deviceID>T2058</deviceID>
    <userID>2599</userID>
    <sdatetimeSTR>10.03.2024 8:33:12</sdatetimeSTR>
    <edatetimeSTR>10.03.2024 20:41:54</edatetimeSTR>
  </operation>
  <operation>
    <deviceID>T2058</deviceID>
    <userID>3145</userID>
    <sdatetimeSTR>14.03.2024 8:27:26</sdatetimeSTR>
    <edatetimeSTR>15.03.2024 2:26:54</edatetimeSTR>
  </operation>
  <operation>
    <deviceID>T2058</deviceID>
    <userID>3247</userID>
    <sdatetimeSTR>15.03.2024 20:33:12</sdatetimeSTR>
    <edatetimeSTR>16.03.2024 8:11:28</edatetimeSTR>
  </operation>
  <operation>
    <deviceID>T2058</deviceID>
    <userID>3247</userID>
    <sdatetimeSTR>18.03.2024 8:39:15</sdatetimeSTR>
    <edatetimeSTR>18.03.2024 20:31:50</edatetimeSTR>
  </operation>
  <operation>
    <deviceID>T2058</deviceID>
    <userID>3255</userID>
    <sdatetimeSTR>19.03.2024 20:45:04</sdatetimeSTR>
    <edatetimeSTR>20.03.2024 8:17:09</edatetimeSTR>
  </operation>
  <operation>
    <deviceID>T2058</deviceID>
    <userID>2251</userID>
    <sdatetimeSTR>22.03.2024 8:31:50</sdatetimeSTR>
    <edatetimeSTR>22.03.2024 19:43:16</edatetimeSTR>
  </operation>
  <operation>
    <deviceID>T2058</deviceID>
    <userID>1463</userID>
    <sdatetimeSTR>26.03.2024 9:19:39</sdatetimeSTR>
    <edatetimeSTR>27.03.2024 9:01:07</edatetimeSTR>
  </operation>
  <operation>
    <deviceID>T2058</deviceID>
    <userID>1936</userID>
    <sdatetimeSTR>28.03.2024 4:18:11</sdatetimeSTR>
    <edatetimeSTR>28.03.2024 8:54:34</edatetimeSTR>
  </operation>
  <operation>
    <deviceID>T2058</deviceID>
    <userID>0261</userID>
    <sdatetimeSTR>30.03.2024 8:27:37</sdatetimeSTR>
    <edatetimeSTR>30.03.2024 18:52:38</edatetimeSTR>
  </operation>
  <operation>
    <deviceID>T2058</deviceID>
    <userID>3145</userID>
    <sdatetimeSTR>03.04.2024 8:42:26</sdatetimeSTR>
    <edatetimeSTR>03.04.2024 20:58:02</edatetimeSTR>
  </operation>
  <operation>
    <deviceID>T2058</deviceID>
    <userID>3232</userID>
    <sdatetimeSTR>05.04.2024 9:01:19</sdatetimeSTR>
    <edatetimeSTR>06.04.2024 0:05:43</edatetimeSTR>
  </operation>
  <operation>
    <deviceID>T2058</deviceID>
    <userID>1452</userID>
    <sdatetimeSTR>07.04.2024 8:20:39</sdatetimeSTR>
    <edatetimeSTR>07.04.2024 20:54:40</edatetimeSTR>
  </operation>
  <operation>
    <deviceID>T2058</deviceID>
    <userID>2211</userID>
    <sdatetimeSTR>11.04.2024 8:31:43</sdatetimeSTR>
    <edatetimeSTR>11.04.2024 17:35:18</edatetimeSTR>
  </operation>
  <operation>
    <deviceID>T2058</deviceID>
    <userID>3210</userID>
    <sdatetimeSTR>12.04.2024 21:05:52</sdatetimeSTR>
    <edatetimeSTR>13.04.2024 8:35:32</edatetimeSTR>
  </operation>
  <operation>
    <deviceID>T2058</deviceID>
    <userID>2211</userID>
    <sdatetimeSTR>15.04.2024 8:38:38</sdatetimeSTR>
    <edatetimeSTR>15.04.2024 17:04:13</edatetimeSTR>
  </operation>
  <operation>
    <deviceID>T2058</deviceID>
    <userID>3136</userID>
    <sdatetimeSTR>17.04.2024 5:26:35</sdatetimeSTR>
    <edatetimeSTR>17.04.2024 8:52:41</edatetimeSTR>
  </operation>
  <operation>
    <deviceID>T2058</deviceID>
    <userID>2452</userID>
    <sdatetimeSTR>19.04.2024 8:47:55</sdatetimeSTR>
    <edatetimeSTR>19.04.2024 9:26:35</edatetimeSTR>
  </operation>
  <operation>
    <deviceID>T2058</deviceID>
    <userID>3282</userID>
    <sdatetimeSTR>19.04.2024 11:22:35</sdatetimeSTR>
    <edatetimeSTR>19.04.2024 21:16:23</edatetimeSTR>
  </operation>
  <operation>
    <deviceID>T2058</deviceID>
    <userID>0123</userID>
    <sdatetimeSTR>20.04.2024 20:21:24</sdatetimeSTR>
    <edatetimeSTR>21.04.2024 8:17:35</edatetimeSTR>
  </operation>
  <operation>
    <deviceID>T2058</deviceID>
    <userID>2127</userID>
    <sdatetimeSTR>25.04.2024 2:05:14</sdatetimeSTR>
    <edatetimeSTR>25.04.2024 8:47:12</edatetimeSTR>
  </operation>
  <operation>
    <deviceID>T2058</deviceID>
    <userID>3377</userID>
    <sdatetimeSTR>27.04.2024 17:39:18</sdatetimeSTR>
    <edatetimeSTR>27.04.2024 20:43:20</edatetimeSTR>
  </operation>
  <operation>
    <deviceID>T2058</deviceID>
    <userID>2048</userID>
    <sdatetimeSTR>27.04.2024 21:08:00</sdatetimeSTR>
    <edatetimeSTR>28.04.2024 4:34:52</edatetimeSTR>
  </operation>
  <operation>
    <deviceID>T2058</deviceID>
    <userID>2211</userID>
    <sdatetimeSTR>01.05.2024 15:38:18</sdatetimeSTR>
    <edatetimeSTR>01.05.2024 20:30:26</edatetimeSTR>
  </operation>
  <operation>
    <deviceID>T2058</deviceID>
    <userID>3145</userID>
    <sdatetimeSTR>02.05.2024 7:09:06</sdatetimeSTR>
    <edatetimeSTR>02.05.2024 8:47:13</edatetimeSTR>
  </operation>
  <operation>
    <deviceID>T2058</deviceID>
    <userID>3210</userID>
    <sdatetimeSTR>02.05.2024 20:24:49</sdatetimeSTR>
    <edatetimeSTR>03.05.2024 7:04:19</edatetimeSTR>
  </operation>
  <operation>
    <deviceID>T2058</deviceID>
    <userID>3255</userID>
    <sdatetimeSTR>05.05.2024 11:04:40</sdatetimeSTR>
    <edatetimeSTR>05.05.2024 20:33:11</edatetimeSTR>
  </operation>
  <operation>
    <deviceID>T2058</deviceID>
    <userID>0261</userID>
    <sdatetimeSTR>09.05.2024 8:32:03</sdatetimeSTR>
    <edatetimeSTR>09.05.2024 16:51:06</edatetimeSTR>
  </operation>
  <operation>
    <deviceID>T2058</deviceID>
    <userID>3649</userID>
    <sdatetimeSTR>09.05.2024 19:56:19</sdatetimeSTR>
    <edatetimeSTR>09.05.2024 20:21:49</edatetimeSTR>
  </operation>
  <operation>
    <deviceID>T2058</deviceID>
    <userID>2567</userID>
    <sdatetimeSTR>09.05.2024 21:10:12</sdatetimeSTR>
    <edatetimeSTR>10.05.2024 1:07:25</edatetimeSTR>
  </operation>
  <operation>
    <deviceID>T2058</deviceID>
    <userID>3156</userID>
    <sdatetimeSTR>10.05.2024 20:28:13</sdatetimeSTR>
    <edatetimeSTR>11.05.2024 8:29:04</edatetimeSTR>
  </operation>
  <operation>
    <deviceID>T2058</deviceID>
    <userID>3691</userID>
    <sdatetimeSTR>15.05.2024 8:43:11</sdatetimeSTR>
    <edatetimeSTR>15.05.2024 20:27:29</edatetimeSTR>
  </operation>
  <operation>
    <deviceID>T2058</deviceID>
    <userID>0016</userID>
    <sdatetimeSTR>19.05.2024 9:11:51</sdatetimeSTR>
    <edatetimeSTR>19.05.2024 22:10:25</edatetimeSTR>
  </operation>
  <operation>
    <deviceID>T2058</deviceID>
    <userID>3260</userID>
    <sdatetimeSTR>20.05.2024 8:49:52</sdatetimeSTR>
    <edatetimeSTR>21.05.2024 7:44:28</edatetimeSTR>
  </operation>
  <operation>
    <deviceID>T2058</deviceID>
    <userID>3298</userID>
    <sdatetimeSTR>21.05.2024 20:58:14</sdatetimeSTR>
    <edatetimeSTR>22.05.2024 8:21:57</edatetimeSTR>
  </operation>
  <operation>
    <deviceID>T2058</deviceID>
    <userID>2200</userID>
    <sdatetimeSTR>22.05.2024 20:50:13</sdatetimeSTR>
    <edatetimeSTR>23.05.2024 8:22:38</edatetimeSTR>
  </operation>
  <operation>
    <deviceID>T2058</deviceID>
    <userID>3547</userID>
    <sdatetimeSTR>25.05.2024 8:28:12</sdatetimeSTR>
    <edatetimeSTR>25.05.2024 20:57:49</edatetimeSTR>
  </operation>
  <operation>
    <deviceID>T2058</deviceID>
    <userID>3112</userID>
    <sdatetimeSTR>26.05.2024 20:23:27</sdatetimeSTR>
    <edatetimeSTR>27.05.2024 2:12:13</edatetimeSTR>
  </operation>
  <operation>
    <deviceID>T2058</deviceID>
    <userID>3163</userID>
    <sdatetimeSTR>29.05.2024 9:06:41</sdatetimeSTR>
    <edatetimeSTR>30.05.2024 8:55:14</edatetimeSTR>
  </operation>
  <operation>
    <deviceID>T2058</deviceID>
    <userID>1287</userID>
    <sdatetimeSTR>30.05.2024 20:23:16</sdatetimeSTR>
    <edatetimeSTR>31.05.2024 8:37:37</edatetimeSTR>
  </operation>
  <operation>
    <deviceID>T2058</deviceID>
    <userID>3953</userID>
    <sdatetimeSTR>02.06.2024 17:54:56</sdatetimeSTR>
    <edatetimeSTR>02.06.2024 20:25:34</edatetimeSTR>
  </operation>
  <operation>
    <deviceID>T2058</deviceID>
    <userID>1399</userID>
    <sdatetimeSTR>10.06.2024 8:34:12</sdatetimeSTR>
    <edatetimeSTR>10.06.2024 20:43:39</edatetimeSTR>
  </operation>
  <operation>
    <deviceID>T2058</deviceID>
    <userID>1759</userID>
    <sdatetimeSTR>11.06.2024 20:37:57</sdatetimeSTR>
    <edatetimeSTR>12.06.2024 2:32:55</edatetimeSTR>
  </operation>
  <operation>
    <deviceID>T2058</deviceID>
    <userID>0968</userID>
    <sdatetimeSTR>14.06.2024 8:41:15</sdatetimeSTR>
    <edatetimeSTR>17.06.2024 13:38:37</edatetimeSTR>
  </operation>
  <operation>
    <deviceID>T2058</deviceID>
    <userID>3191</userID>
    <sdatetimeSTR>03.07.2024 8:28:25</sdatetimeSTR>
    <edatetimeSTR>04.07.2024 8:17:38</edatetimeSTR>
  </operation>
  <operation>
    <deviceID>T2058</deviceID>
    <userID>3902</userID>
    <sdatetimeSTR>04.07.2024 19:22:13</sdatetimeSTR>
    <edatetimeSTR>04.07.2024 20:53:40</edatetimeSTR>
  </operation>
  <operation>
    <deviceID>T2058</deviceID>
    <userID>0896</userID>
    <sdatetimeSTR>05.07.2024 20:46:11</sdatetimeSTR>
    <edatetimeSTR>05.07.2024 20:58:28</edatetimeSTR>
  </operation>
  <operation>
    <deviceID>T2058</deviceID>
    <userID>0261</userID>
    <sdatetimeSTR>14.07.2024 5:24:07</sdatetimeSTR>
    <edatetimeSTR>14.07.2024 8:19:38</edatetimeSTR>
  </operation>
  <operation>
    <deviceID>T2058</deviceID>
    <userID>3255</userID>
    <sdatetimeSTR>18.07.2024 3:35:27</sdatetimeSTR>
    <edatetimeSTR>18.07.2024 8:45:26</edatetimeSTR>
  </operation>
  <operation>
    <deviceID>T2058</deviceID>
    <userID>3502</userID>
    <sdatetimeSTR>20.07.2024 14:16:13</sdatetimeSTR>
    <edatetimeSTR>20.07.2024 21:03:41</edatetimeSTR>
  </operation>
  <operation>
    <deviceID>T2058</deviceID>
    <userID>3502</userID>
    <sdatetimeSTR>22.07.2024 2:52:57</sdatetimeSTR>
    <edatetimeSTR>22.07.2024 8:53:35</edatetimeSTR>
  </operation>
  <operation>
    <deviceID>T2058</deviceID>
    <userID>3742</userID>
    <sdatetimeSTR>24.07.2024 17:47:55</sdatetimeSTR>
    <edatetimeSTR>24.07.2024 20:50:37</edatetimeSTR>
  </operation>
  <operation>
    <deviceID>T2058</deviceID>
    <userID>2127</userID>
    <sdatetimeSTR>25.07.2024 20:46:53</sdatetimeSTR>
    <edatetimeSTR>26.07.2024 7:55:12</edatetimeSTR>
  </operation>
  <operation>
    <deviceID>T2058</deviceID>
    <userID>3817</userID>
    <sdatetimeSTR>27.07.2024 9:19:32</sdatetimeSTR>
    <edatetimeSTR>27.07.2024 21:24:03</edatetimeSTR>
  </operation>
  <operation>
    <deviceID>T2058</deviceID>
    <userID>0123</userID>
    <sdatetimeSTR>03.08.2024 23:56:22</sdatetimeSTR>
    <edatetimeSTR>04.08.2024 8:35:12</edatetimeSTR>
  </operation>
  <operation>
    <deviceID>T2058</deviceID>
    <userID>3953</userID>
    <sdatetimeSTR>05.08.2024 17:19:59</sdatetimeSTR>
    <edatetimeSTR>07.08.2024 0:03:06</edatetimeSTR>
  </operation>
  <operation>
    <deviceID>T2058</deviceID>
    <userID>3164</userID>
    <sdatetimeSTR>08.08.2024 20:38:37</sdatetimeSTR>
    <edatetimeSTR>09.08.2024 6:52:52</edatetimeSTR>
  </operation>
  <operation>
    <deviceID>T2058</deviceID>
    <userID>1473</userID>
    <sdatetimeSTR>09.08.2024 15:33:53</sdatetimeSTR>
    <edatetimeSTR>09.08.2024 20:20:01</edatetimeSTR>
  </operation>
  <operation>
    <deviceID>T2058</deviceID>
    <userID>0123</userID>
    <sdatetimeSTR>10.08.2024 8:18:51</sdatetimeSTR>
    <edatetimeSTR>10.08.2024 21:16:15</edatetimeSTR>
  </operation>
  <operation>
    <deviceID>T2058</deviceID>
    <userID>1449</userID>
    <sdatetimeSTR>11.08.2024 13:55:41</sdatetimeSTR>
    <edatetimeSTR>11.08.2024 20:46:32</edatetimeSTR>
  </operation>
  <operation>
    <deviceID>T2058</deviceID>
    <userID>3131</userID>
    <sdatetimeSTR>13.08.2024 8:50:31</sdatetimeSTR>
    <edatetimeSTR>13.08.2024 18:51:01</edatetimeSTR>
  </operation>
  <operation>
    <deviceID>T2058</deviceID>
    <userID>3255</userID>
    <sdatetimeSTR>21.08.2024 8:48:09</sdatetimeSTR>
    <edatetimeSTR>21.08.2024 14:42:08</edatetimeSTR>
  </operation>
  <operation>
    <deviceID>T2058</deviceID>
    <userID>1309</userID>
    <sdatetimeSTR>21.08.2024 17:38:18</sdatetimeSTR>
    <edatetimeSTR>21.08.2024 20:40:20</edatetimeSTR>
  </operation>
  <operation>
    <deviceID>T2058</deviceID>
    <userID>0149</userID>
    <sdatetimeSTR>22.08.2024 20:17:17</sdatetimeSTR>
    <edatetimeSTR>23.08.2024 2:55:46</edatetimeSTR>
  </operation>
  <operation>
    <deviceID>T2058</deviceID>
    <userID>2098</userID>
    <sdatetimeSTR>26.08.2024 20:10:24</sdatetimeSTR>
    <edatetimeSTR>27.08.2024 8:45:42</edatetimeSTR>
  </operation>
  <operation>
    <deviceID>T2058</deviceID>
    <userID>2468</userID>
    <sdatetimeSTR>28.08.2024 8:39:42</sdatetimeSTR>
    <edatetimeSTR>29.08.2024 7:52:04</edatetimeSTR>
  </operation>
  <operation>
    <deviceID>T2058</deviceID>
    <userID>0149</userID>
    <sdatetimeSTR>02.09.2024 17:33:56</sdatetimeSTR>
    <edatetimeSTR>02.09.2024 20:43:13</edatetimeSTR>
  </operation>
  <operation>
    <deviceID>T2058</deviceID>
    <userID>0404</userID>
    <sdatetimeSTR>03.09.2024 9:04:50</sdatetimeSTR>
    <edatetimeSTR>04.09.2024 9:00:10</edatetimeSTR>
  </operation>
  <operation>
    <deviceID>T2058</deviceID>
    <userID>3247</userID>
    <sdatetimeSTR>15.09.2024 20:23:42</sdatetimeSTR>
    <edatetimeSTR>16.09.2024 3:22:58</edatetimeSTR>
  </operation>
  <operation>
    <deviceID>T2058</deviceID>
    <userID>3533</userID>
    <sdatetimeSTR>18.09.2024 8:46:34</sdatetimeSTR>
    <edatetimeSTR>18.09.2024 20:41:55</edatetimeSTR>
  </operation>
  <operation>
    <deviceID>T2058</deviceID>
    <userID>3156</userID>
    <sdatetimeSTR>19.09.2024 20:14:22</sdatetimeSTR>
    <edatetimeSTR>20.09.2024 3:14:08</edatetimeSTR>
  </operation>
  <operation>
    <deviceID>T2058</deviceID>
    <userID>0151</userID>
    <sdatetimeSTR>20.09.2024 9:08:23</sdatetimeSTR>
    <edatetimeSTR>21.09.2024 8:42:46</edatetimeSTR>
  </operation>
  <operation>
    <deviceID>T2058</deviceID>
    <userID>1383</userID>
    <sdatetimeSTR>21.09.2024 18:39:38</sdatetimeSTR>
    <edatetimeSTR>21.09.2024 20:34:53</edatetimeSTR>
  </operation>
  <operation>
    <deviceID>T2058</deviceID>
    <userID>1287</userID>
    <sdatetimeSTR>22.09.2024 8:35:51</sdatetimeSTR>
    <edatetimeSTR>22.09.2024 20:29:15</edatetimeSTR>
  </operation>
  <operation>
    <deviceID>T2058</deviceID>
    <userID>1936</userID>
    <sdatetimeSTR>23.09.2024 20:42:30</sdatetimeSTR>
    <edatetimeSTR>24.09.2024 8:54:49</edatetimeSTR>
  </operation>
  <operation>
    <deviceID>T2058</deviceID>
    <userID>1399</userID>
    <sdatetimeSTR>26.09.2024 8:37:35</sdatetimeSTR>
    <edatetimeSTR>26.09.2024 20:47:08</edatetimeSTR>
  </operation>
  <operation>
    <deviceID>T2058</deviceID>
    <userID>1862</userID>
    <sdatetimeSTR>03.10.2024 11:57:13</sdatetimeSTR>
    <edatetimeSTR>03.10.2024 14:54:09</edatetimeSTR>
  </operation>
  <operation>
    <deviceID>T2058</deviceID>
    <userID>2892</userID>
    <sdatetimeSTR>03.10.2024 20:54:35</sdatetimeSTR>
    <edatetimeSTR>04.10.2024 8:48:39</edatetimeSTR>
  </operation>
  <operation>
    <deviceID>T2058</deviceID>
    <userID>1473</userID>
    <sdatetimeSTR>04.10.2024 20:02:29</sdatetimeSTR>
    <edatetimeSTR>04.10.2024 20:43:46</edatetimeSTR>
  </operation>
  <operation>
    <deviceID>T2058</deviceID>
    <userID>2127</userID>
    <sdatetimeSTR>08.10.2024 8:20:02</sdatetimeSTR>
    <edatetimeSTR>08.10.2024 20:34:41</edatetimeSTR>
  </operation>
  <operation>
    <deviceID>T2058</deviceID>
    <userID>2932</userID>
    <sdatetimeSTR>09.10.2024 9:19:37</sdatetimeSTR>
    <edatetimeSTR>10.10.2024 8:12:11</edatetimeSTR>
  </operation>
  <operation>
    <deviceID>T2058</deviceID>
    <userID>1518</userID>
    <sdatetimeSTR>10.10.2024 8:29:55</sdatetimeSTR>
    <edatetimeSTR>10.10.2024 23:29:50</edatetimeSTR>
  </operation>
  <operation>
    <deviceID>T2058</deviceID>
    <userID>3538</userID>
    <sdatetimeSTR>11.10.2024 4:47:24</sdatetimeSTR>
    <edatetimeSTR>11.10.2024 8:22:00</edatetimeSTR>
  </operation>
  <operation>
    <deviceID>T2058</deviceID>
    <userID>0586</userID>
    <sdatetimeSTR>11.10.2024 8:22:52</sdatetimeSTR>
    <edatetimeSTR>11.10.2024 16:21:48</edatetimeSTR>
  </operation>
  <operation>
    <deviceID>T2058</deviceID>
    <userID>0676</userID>
    <sdatetimeSTR>12.10.2024 8:40:25</sdatetimeSTR>
    <edatetimeSTR>12.10.2024 21:07:07</edatetimeSTR>
  </operation>
  <operation>
    <deviceID>T2058</deviceID>
    <userID>2056</userID>
    <sdatetimeSTR>14.10.2024 9:14:23</sdatetimeSTR>
    <edatetimeSTR>15.10.2024 8:23:43</edatetimeSTR>
  </operation>
  <operation>
    <deviceID>T2058</deviceID>
    <userID>0676</userID>
    <sdatetimeSTR>17.10.2024 21:05:51</sdatetimeSTR>
    <edatetimeSTR>18.10.2024 4:19:51</edatetimeSTR>
  </operation>
  <operation>
    <deviceID>T2058</deviceID>
    <userID>3502</userID>
    <sdatetimeSTR>18.10.2024 5:37:41</sdatetimeSTR>
    <edatetimeSTR>18.10.2024 9:09:18</edatetimeSTR>
  </operation>
  <operation>
    <deviceID>T2058</deviceID>
    <userID>2359</userID>
    <sdatetimeSTR>18.10.2024 20:25:02</sdatetimeSTR>
    <edatetimeSTR>19.10.2024 8:43:18</edatetimeSTR>
  </operation>
  <operation>
    <deviceID>T2058</deviceID>
    <userID>3060</userID>
    <sdatetimeSTR>19.10.2024 20:46:53</sdatetimeSTR>
    <edatetimeSTR>20.10.2024 8:42:10</edatetimeSTR>
  </operation>
  <operation>
    <deviceID>T2058</deviceID>
    <userID>3832</userID>
    <sdatetimeSTR>20.10.2024 17:39:30</sdatetimeSTR>
    <edatetimeSTR>20.10.2024 20:49:15</edatetimeSTR>
  </operation>
  <operation>
    <deviceID>T2058</deviceID>
    <userID>0149</userID>
    <sdatetimeSTR>22.10.2024 5:50:55</sdatetimeSTR>
    <edatetimeSTR>22.10.2024 8:45:23</edatetimeSTR>
  </operation>
  <operation>
    <deviceID>T2058</deviceID>
    <userID>1529</userID>
    <sdatetimeSTR>22.10.2024 20:30:51</sdatetimeSTR>
    <edatetimeSTR>23.10.2024 8:33:46</edatetimeSTR>
  </operation>
  <operation>
    <deviceID>T2058</deviceID>
    <userID>3209</userID>
    <sdatetimeSTR>23.10.2024 23:54:06</sdatetimeSTR>
    <edatetimeSTR>24.10.2024 8:56:56</edatetimeSTR>
  </operation>
  <operation>
    <deviceID>T2058</deviceID>
    <userID>3690</userID>
    <sdatetimeSTR>26.10.2024 9:51:24</sdatetimeSTR>
    <edatetimeSTR>26.10.2024 20:49:23</edatetimeSTR>
  </operation>
  <operation>
    <deviceID>T2058</deviceID>
    <userID>0384</userID>
    <sdatetimeSTR>27.10.2024 3:55:04</sdatetimeSTR>
    <edatetimeSTR>27.10.2024 8:37:04</edatetimeSTR>
  </operation>
  <operation>
    <deviceID>T2058</deviceID>
    <userID>3632</userID>
    <sdatetimeSTR>28.10.2024 8:51:14</sdatetimeSTR>
    <edatetimeSTR>28.10.2024 16:02:11</edatetimeSTR>
  </operation>
  <operation>
    <deviceID>T2058</deviceID>
    <userID>3885</userID>
    <sdatetimeSTR>30.10.2024 9:14:36</sdatetimeSTR>
    <edatetimeSTR>30.10.2024 20:56:41</edatetimeSTR>
  </operation>
  <operation>
    <deviceID>T2058</deviceID>
    <userID>2250</userID>
    <sdatetimeSTR>31.10.2024 4:32:19</sdatetimeSTR>
    <edatetimeSTR>31.10.2024 4:36:03</edatetimeSTR>
  </operation>
  <operation>
    <deviceID>T2058</deviceID>
    <userID>0123</userID>
    <sdatetimeSTR>31.10.2024 9:11:44</sdatetimeSTR>
    <edatetimeSTR>31.10.2024 17:48:48</edatetimeSTR>
  </operation>
  <operation>
    <deviceID>T2058</deviceID>
    <userID>3953</userID>
    <sdatetimeSTR>01.11.2024 11:24:18</sdatetimeSTR>
    <edatetimeSTR>01.11.2024 21:02:28</edatetimeSTR>
  </operation>
  <operation>
    <deviceID>T2058</deviceID>
    <userID>3071</userID>
    <sdatetimeSTR>02.11.2024 20:49:45</sdatetimeSTR>
    <edatetimeSTR>03.11.2024 8:54:42</edatetimeSTR>
  </operation>
  <operation>
    <deviceID>T2058</deviceID>
    <userID>3715</userID>
    <sdatetimeSTR>04.11.2024 2:00:36</sdatetimeSTR>
    <edatetimeSTR>04.11.2024 8:54:22</edatetimeSTR>
  </operation>
  <operation>
    <deviceID>T2058</deviceID>
    <userID>3898</userID>
    <sdatetimeSTR>06.11.2024 20:12:38</sdatetimeSTR>
    <edatetimeSTR>07.11.2024 8:47:32</edatetimeSTR>
  </operation>
  <operation>
    <deviceID>T2058</deviceID>
    <userID>0123</userID>
    <sdatetimeSTR>07.11.2024 20:11:53</sdatetimeSTR>
    <edatetimeSTR>08.11.2024 9:02:39</edatetimeSTR>
  </operation>
  <operation>
    <deviceID>T2058</deviceID>
    <userID>3065</userID>
    <sdatetimeSTR>09.11.2024 8:24:58</sdatetimeSTR>
    <edatetimeSTR>09.11.2024 20:59:38</edatetimeSTR>
  </operation>
  <operation>
    <deviceID>T2058</deviceID>
    <userID>1198</userID>
    <sdatetimeSTR>10.11.2024 9:02:27</sdatetimeSTR>
    <edatetimeSTR>10.11.2024 18:45:37</edatetimeSTR>
  </operation>
  <operation>
    <deviceID>T2058</deviceID>
    <userID>0123</userID>
    <sdatetimeSTR>11.11.2024 9:38:12</sdatetimeSTR>
    <edatetimeSTR>11.11.2024 20:35:37</edatetimeSTR>
  </operation>
  <operation>
    <deviceID>T2058</deviceID>
    <userID>1000</userID>
    <sdatetimeSTR>13.11.2024 8:43:31</sdatetimeSTR>
    <edatetimeSTR>13.11.2024 17:28:50</edatetimeSTR>
  </operation>
  <operation>
    <deviceID>T2058</deviceID>
    <userID>3231</userID>
    <sdatetimeSTR>13.11.2024 21:46:18</sdatetimeSTR>
    <edatetimeSTR>14.11.2024 8:45:00</edatetimeSTR>
  </operation>
  <operation>
    <deviceID>T2058</deviceID>
    <userID>2274</userID>
    <sdatetimeSTR>15.11.2024 20:32:44</sdatetimeSTR>
    <edatetimeSTR>16.11.2024 8:19:16</edatetimeSTR>
  </operation>
  <operation>
    <deviceID>T2058</deviceID>
    <userID>3231</userID>
    <sdatetimeSTR>19.11.2024 8:18:30</sdatetimeSTR>
    <edatetimeSTR>19.11.2024 20:48:14</edatetimeSTR>
  </operation>
  <operation>
    <deviceID>T2058</deviceID>
    <userID>2661</userID>
    <sdatetimeSTR>20.11.2024 9:13:33</sdatetimeSTR>
    <edatetimeSTR>20.11.2024 20:31:30</edatetimeSTR>
  </operation>
  <operation>
    <deviceID>T2058</deviceID>
    <userID>3730</userID>
    <sdatetimeSTR>20.11.2024 20:32:53</sdatetimeSTR>
    <edatetimeSTR>21.11.2024 3:58:43</edatetimeSTR>
  </operation>
  <operation>
    <deviceID>T2058</deviceID>
    <userID>0149</userID>
    <sdatetimeSTR>21.11.2024 8:37:36</sdatetimeSTR>
    <edatetimeSTR>21.11.2024 20:43:12</edatetimeSTR>
  </operation>
  <operation>
    <deviceID>T2058</deviceID>
    <userID>3168</userID>
    <sdatetimeSTR>22.11.2024 8:40:58</sdatetimeSTR>
    <edatetimeSTR>22.11.2024 20:23:16</edatetimeSTR>
  </operation>
  <operation>
    <deviceID>T2058</deviceID>
    <userID>1000</userID>
    <sdatetimeSTR>23.11.2024 4:32:51</sdatetimeSTR>
    <edatetimeSTR>23.11.2024 8:20:19</edatetimeSTR>
  </operation>
  <operation>
    <deviceID>T2058</deviceID>
    <userID>2976</userID>
    <sdatetimeSTR>23.11.2024 20:35:19</sdatetimeSTR>
    <edatetimeSTR>24.11.2024 4:34:44</edatetimeSTR>
  </operation>
  <operation>
    <deviceID>T2058</deviceID>
    <userID>1001</userID>
    <sdatetimeSTR>24.11.2024 8:47:26</sdatetimeSTR>
    <edatetimeSTR>24.11.2024 16:10:30</edatetimeSTR>
  </operation>
  <operation>
    <deviceID>T2058</deviceID>
    <userID>1233</userID>
    <sdatetimeSTR>24.11.2024 20:28:56</sdatetimeSTR>
    <edatetimeSTR>25.11.2024 7:06:22</edatetimeSTR>
  </operation>
  <operation>
    <deviceID>T2058</deviceID>
    <userID>3255</userID>
    <sdatetimeSTR>26.11.2024 20:44:31</sdatetimeSTR>
    <edatetimeSTR>27.11.2024 4:06:08</edatetimeSTR>
  </operation>
  <operation>
    <deviceID>T2058</deviceID>
    <userID>1513</userID>
    <sdatetimeSTR>27.11.2024 9:42:52</sdatetimeSTR>
    <edatetimeSTR>27.11.2024 20:51:17</edatetimeSTR>
  </operation>
  <operation>
    <deviceID>T2058</deviceID>
    <userID>3648</userID>
    <sdatetimeSTR>28.11.2024 10:17:49</sdatetimeSTR>
    <edatetimeSTR>28.11.2024 20:24:29</edatetimeSTR>
  </operation>
  <operation>
    <deviceID>T2058</deviceID>
    <userID>3313</userID>
    <sdatetimeSTR>29.11.2024 5:59:57</sdatetimeSTR>
    <edatetimeSTR>29.11.2024 8:52:51</edatetimeSTR>
  </operation>
  <operation>
    <deviceID>T2058</deviceID>
    <userID>1936</userID>
    <sdatetimeSTR>29.11.2024 8:58:06</sdatetimeSTR>
    <edatetimeSTR>29.11.2024 18:52:13</edatetimeSTR>
  </operation>
  <operation>
    <deviceID>T2058</deviceID>
    <userID>3550</userID>
    <sdatetimeSTR>30.11.2024 9:06:20</sdatetimeSTR>
    <edatetimeSTR>30.11.2024 13:34:19</edatetimeSTR>
  </operation>
  <operation>
    <deviceID>T2058</deviceID>
    <userID>1739</userID>
    <sdatetimeSTR>30.11.2024 17:51:49</sdatetimeSTR>
    <edatetimeSTR>30.11.2024 20:37:27</edatetimeSTR>
  </operation>
  <operation>
    <deviceID>T2058</deviceID>
    <userID>0261</userID>
    <sdatetimeSTR>01.12.2024 4:08:30</sdatetimeSTR>
    <edatetimeSTR>01.12.2024 8:43:32</edatetimeSTR>
  </operation>
  <operation>
    <deviceID>T2058</deviceID>
    <userID>3648</userID>
    <sdatetimeSTR>02.12.2024 8:36:06</sdatetimeSTR>
    <edatetimeSTR>02.12.2024 18:08:09</edatetimeSTR>
  </operation>
  <operation>
    <deviceID>T2058</deviceID>
    <userID>3255</userID>
    <sdatetimeSTR>03.12.2024 8:47:34</sdatetimeSTR>
    <edatetimeSTR>03.12.2024 20:24:15</edatetimeSTR>
  </operation>
  <operation>
    <deviceID>T2058</deviceID>
    <userID>3207</userID>
    <sdatetimeSTR>04.12.2024 2:59:28</sdatetimeSTR>
    <edatetimeSTR>04.12.2024 8:52:24</edatetimeSTR>
  </operation>
  <operation>
    <deviceID>T2058</deviceID>
    <userID>0123</userID>
    <sdatetimeSTR>04.12.2024 9:13:10</sdatetimeSTR>
    <edatetimeSTR>04.12.2024 20:42:31</edatetimeSTR>
  </operation>
  <operation>
    <deviceID>T2058</deviceID>
    <userID>1309</userID>
    <sdatetimeSTR>05.12.2024 3:06:26</sdatetimeSTR>
    <edatetimeSTR>05.12.2024 8:32:00</edatetimeSTR>
  </operation>
  <operation>
    <deviceID>T2058</deviceID>
    <userID>1116</userID>
    <sdatetimeSTR>05.12.2024 20:27:31</sdatetimeSTR>
    <edatetimeSTR>06.12.2024 9:06:46</edatetimeSTR>
  </operation>
  <operation>
    <deviceID>T2058</deviceID>
    <userID>3599</userID>
    <sdatetimeSTR>07.12.2024 8:13:54</sdatetimeSTR>
    <edatetimeSTR>07.12.2024 20:52:13</edatetimeSTR>
  </operation>
  <operation>
    <deviceID>T2058</deviceID>
    <userID>2048</userID>
    <sdatetimeSTR>08.12.2024 3:05:39</sdatetimeSTR>
    <edatetimeSTR>08.12.2024 8:26:40</edatetimeSTR>
  </operation>
  <operation>
    <deviceID>T2058</deviceID>
    <userID>0384</userID>
    <sdatetimeSTR>08.12.2024 8:29:51</sdatetimeSTR>
    <edatetimeSTR>08.12.2024 20:46:23</edatetimeSTR>
  </operation>
  <operation>
    <deviceID>T2058</deviceID>
    <userID>0261</userID>
    <sdatetimeSTR>09.12.2024 7:28:05</sdatetimeSTR>
    <edatetimeSTR>09.12.2024 8:28:05</edatetimeSTR>
  </operation>
  <operation>
    <deviceID>T2058</deviceID>
    <userID>2111</userID>
    <sdatetimeSTR>09.12.2024 8:31:31</sdatetimeSTR>
    <edatetimeSTR>09.12.2024 20:50:27</edatetimeSTR>
  </operation>
  <operation>
    <deviceID>T2058</deviceID>
    <userID>1399</userID>
    <sdatetimeSTR>10.12.2024 8:35:32</sdatetimeSTR>
    <edatetimeSTR>10.12.2024 20:29:45</edatetimeSTR>
  </operation>
  <operation>
    <deviceID>T2058</deviceID>
    <userID>0123</userID>
    <sdatetimeSTR>11.12.2024 5:59:28</sdatetimeSTR>
    <edatetimeSTR>11.12.2024 8:38:36</edatetimeSTR>
  </operation>
  <operation>
    <deviceID>T2058</deviceID>
    <userID>0261</userID>
    <sdatetimeSTR>11.12.2024 14:23:24</sdatetimeSTR>
    <edatetimeSTR>12.12.2024 0:17:05</edatetimeSTR>
  </operation>
  <operation>
    <deviceID>T2058</deviceID>
    <userID>2359</userID>
    <sdatetimeSTR>12.12.2024 8:33:21</sdatetimeSTR>
    <edatetimeSTR>12.12.2024 20:50:31</edatetimeSTR>
  </operation>
  <operation>
    <deviceID>T2058</deviceID>
    <userID>3482</userID>
    <sdatetimeSTR>13.12.2024 4:56:51</sdatetimeSTR>
    <edatetimeSTR>13.12.2024 8:31:40</edatetimeSTR>
  </operation>
  <operation>
    <deviceID>T2058</deviceID>
    <userID>2111</userID>
    <sdatetimeSTR>13.12.2024 20:57:25</sdatetimeSTR>
    <edatetimeSTR>14.12.2024 4:14:54</edatetimeSTR>
  </operation>
  <operation>
    <deviceID>T2058</deviceID>
    <userID>1795</userID>
    <sdatetimeSTR>14.12.2024 8:43:32</sdatetimeSTR>
    <edatetimeSTR>14.12.2024 20:21:34</edatetimeSTR>
  </operation>
  <operation>
    <deviceID>T2058</deviceID>
    <userID>0202</userID>
    <sdatetimeSTR>15.12.2024 8:23:55</sdatetimeSTR>
    <edatetimeSTR>15.12.2024 20:36:09</edatetimeSTR>
  </operation>
  <operation>
    <deviceID>T2058</deviceID>
    <userID>3271</userID>
    <sdatetimeSTR>16.12.2024 20:30:53</sdatetimeSTR>
    <edatetimeSTR>17.12.2024 4:13:18</edatetimeSTR>
  </operation>
  <operation>
    <deviceID>T2058</deviceID>
    <userID>3486</userID>
    <sdatetimeSTR>17.12.2024 8:44:45</sdatetimeSTR>
    <edatetimeSTR>17.12.2024 20:44:07</edatetimeSTR>
  </operation>
  <operation>
    <deviceID>T2058</deviceID>
    <userID>3211</userID>
    <sdatetimeSTR>18.12.2024 8:58:08</sdatetimeSTR>
    <edatetimeSTR>18.12.2024 20:53:26</edatetimeSTR>
  </operation>
  <operation>
    <deviceID>T2058</deviceID>
    <userID>3953</userID>
    <sdatetimeSTR>19.12.2024 8:23:35</sdatetimeSTR>
    <edatetimeSTR>19.12.2024 17:19:23</edatetimeSTR>
  </operation>
  <operation>
    <deviceID>T2058</deviceID>
    <userID>0123</userID>
    <sdatetimeSTR>19.12.2024 19:25:19</sdatetimeSTR>
    <edatetimeSTR>19.12.2024 20:52:36</edatetimeSTR>
  </operation>
  <operation>
    <deviceID>T2058</deviceID>
    <userID>3211</userID>
    <sdatetimeSTR>20.12.2024 20:44:02</sdatetimeSTR>
    <edatetimeSTR>21.12.2024 8:46:52</edatetimeSTR>
  </operation>
  <operation>
    <deviceID>T2058</deviceID>
    <userID>2083</userID>
    <sdatetimeSTR>21.12.2024 20:36:27</sdatetimeSTR>
    <edatetimeSTR>22.12.2024 7:12:27</edatetimeSTR>
  </operation>
  <operation>
    <deviceID>T2058</deviceID>
    <userID>0123</userID>
    <sdatetimeSTR>22.12.2024 12:37:22</sdatetimeSTR>
    <edatetimeSTR>22.12.2024 20:43:34</edatetimeSTR>
  </operation>
  <operation>
    <deviceID>T2058</deviceID>
    <userID>3519</userID>
    <sdatetimeSTR>23.12.2024 8:27:44</sdatetimeSTR>
    <edatetimeSTR>23.12.2024 21:08:09</edatetimeSTR>
  </operation>
  <operation>
    <deviceID>T2058</deviceID>
    <userID>3831</userID>
    <sdatetimeSTR>24.12.2024 8:50:36</sdatetimeSTR>
    <edatetimeSTR>24.12.2024 18:57:17</edatetimeSTR>
  </operation>
  <operation>
    <deviceID>T2058</deviceID>
    <userID>0123</userID>
    <sdatetimeSTR>24.12.2024 21:03:35</sdatetimeSTR>
    <edatetimeSTR>25.12.2024 4:38:35</edatetimeSTR>
  </operation>
  <operation>
    <deviceID>T2058</deviceID>
    <userID>0123</userID>
    <sdatetimeSTR>25.12.2024 11:48:46</sdatetimeSTR>
    <edatetimeSTR>26.12.2024 3:55:16</edatetimeSTR>
  </operation>
  <operation>
    <deviceID>T2058</deviceID>
    <userID>3466</userID>
    <sdatetimeSTR>25.12.2024 20:48:50</sdatetimeSTR>
    <edatetimeSTR>26.12.2024 3:55:16</edatetimeSTR>
  </operation>
  <operation>
    <deviceID>T2058</deviceID>
    <userID>3839</userID>
    <sdatetimeSTR>26.12.2024 8:32:48</sdatetimeSTR>
    <edatetimeSTR>26.12.2024 15:39:02</edatetimeSTR>
  </operation>
  <operation>
    <deviceID>T2058</deviceID>
    <userID>0149</userID>
    <sdatetimeSTR>26.12.2024 17:27:28</sdatetimeSTR>
    <edatetimeSTR>26.12.2024 20:32:18</edatetimeSTR>
  </operation>
  <operation>
    <deviceID>T2058</deviceID>
    <userID>3351</userID>
    <sdatetimeSTR>27.12.2024 3:33:41</sdatetimeSTR>
    <edatetimeSTR>27.12.2024 8:54:27</edatetimeSTR>
  </operation>
  <operation>
    <deviceID>T2058</deviceID>
    <userID>3599</userID>
    <sdatetimeSTR>28.12.2024 8:11:44</sdatetimeSTR>
    <edatetimeSTR>28.12.2024 21:31:40</edatetimeSTR>
  </operation>
  <operation>
    <deviceID>T2058</deviceID>
    <userID>1001</userID>
    <sdatetimeSTR>30.12.2024 8:35:48</sdatetimeSTR>
    <edatetimeSTR>30.12.2024 17:09:09</edatetimeSTR>
  </operation>
  <operation>
    <deviceID>T2058</deviceID>
    <userID>3885</userID>
    <sdatetimeSTR>02.01.2025 9:11:49</sdatetimeSTR>
    <edatetimeSTR>03.01.2025 8:54:31</edatetimeSTR>
  </operation>
  <operation>
    <deviceID>T2058</deviceID>
    <userID>3148</userID>
    <sdatetimeSTR>04.01.2025 21:13:11</sdatetimeSTR>
    <edatetimeSTR>05.01.2025 6:08:10</edatetimeSTR>
  </operation>
  <operation>
    <deviceID>T2058</deviceID>
    <userID>3056</userID>
    <sdatetimeSTR>07.01.2025 18:40:17</sdatetimeSTR>
    <edatetimeSTR>07.01.2025 20:31:16</edatetimeSTR>
  </operation>
  <operation>
    <deviceID>T2058</deviceID>
    <userID>1309</userID>
    <sdatetimeSTR>08.01.2025 17:38:35</sdatetimeSTR>
    <edatetimeSTR>08.01.2025 20:29:15</edatetimeSTR>
  </operation>
  <operation>
    <deviceID>T2058</deviceID>
    <userID>0676</userID>
    <sdatetimeSTR>09.01.2025 9:08:16</sdatetimeSTR>
    <edatetimeSTR>09.01.2025 18:34:49</edatetimeSTR>
  </operation>
  <operation>
    <deviceID>T2058</deviceID>
    <userID>2111</userID>
    <sdatetimeSTR>10.01.2025 18:07:07</sdatetimeSTR>
    <edatetimeSTR>10.01.2025 20:40:56</edatetimeSTR>
  </operation>
  <operation>
    <deviceID>T2058</deviceID>
    <userID>0123</userID>
    <sdatetimeSTR>11.01.2025 1:50:59</sdatetimeSTR>
    <edatetimeSTR>11.01.2025 9:06:07</edatetimeSTR>
  </operation>
  <operation>
    <deviceID>T2058</deviceID>
    <userID>1000</userID>
    <sdatetimeSTR>12.01.2025 18:13:07</sdatetimeSTR>
    <edatetimeSTR>12.01.2025 20:45:36</edatetimeSTR>
  </operation>
  <operation>
    <deviceID>T2058</deviceID>
    <userID>3751</userID>
    <sdatetimeSTR>15.01.2025 9:49:04</sdatetimeSTR>
    <edatetimeSTR>15.01.2025 9:52:20</edatetimeSTR>
  </operation>
  <operation>
    <deviceID>T2058</deviceID>
    <userID>0123</userID>
    <sdatetimeSTR>15.01.2025 15:33:05</sdatetimeSTR>
    <edatetimeSTR>15.01.2025 20:10:24</edatetimeSTR>
  </operation>
  <operation>
    <deviceID>T2058</deviceID>
    <userID>0261</userID>
    <sdatetimeSTR>16.01.2025 8:39:47</sdatetimeSTR>
    <edatetimeSTR>16.01.2025 17:46:09</edatetimeSTR>
  </operation>
  <operation>
    <deviceID>T2058</deviceID>
    <userID>1465</userID>
    <sdatetimeSTR>19.01.2025 14:28:14</sdatetimeSTR>
    <edatetimeSTR>19.01.2025 16:50:45</edatetimeSTR>
  </operation>
  <operation>
    <deviceID>T2058</deviceID>
    <userID>2609</userID>
    <sdatetimeSTR>19.01.2025 18:30:49</sdatetimeSTR>
    <edatetimeSTR>19.01.2025 20:56:45</edatetimeSTR>
  </operation>
  <operation>
    <deviceID>T2058</deviceID>
    <userID>1472</userID>
    <sdatetimeSTR>20.01.2025 20:58:17</sdatetimeSTR>
    <edatetimeSTR>21.01.2025 8:57:38</edatetimeSTR>
  </operation>
  <operation>
    <deviceID>T2058</deviceID>
    <userID>3692</userID>
    <sdatetimeSTR>22.01.2025 6:58:36</sdatetimeSTR>
    <edatetimeSTR>22.01.2025 8:26:57</edatetimeSTR>
  </operation>
  <operation>
    <deviceID>T2058</deviceID>
    <userID>0053</userID>
    <sdatetimeSTR>24.01.2025 8:48:51</sdatetimeSTR>
    <edatetimeSTR>24.01.2025 17:18:11</edatetimeSTR>
  </operation>
  <operation>
    <deviceID>T2058</deviceID>
    <userID>3446</userID>
    <sdatetimeSTR>25.01.2025 9:02:04</sdatetimeSTR>
    <edatetimeSTR>25.01.2025 18:14:15</edatetimeSTR>
  </operation>
  <operation>
    <deviceID>T2058</deviceID>
    <userID>0123</userID>
    <sdatetimeSTR>26.01.2025 20:53:06</sdatetimeSTR>
    <edatetimeSTR>27.01.2025 8:52:47</edatetimeSTR>
  </operation>
  <operation>
    <deviceID>T2058</deviceID>
    <userID>3097</userID>
    <sdatetimeSTR>27.01.2025 13:45:48</sdatetimeSTR>
    <edatetimeSTR>27.01.2025 20:40:46</edatetimeSTR>
  </operation>
  <operation>
    <deviceID>T2058</deviceID>
    <userID>0896</userID>
    <sdatetimeSTR>28.01.2025 8:32:11</sdatetimeSTR>
    <edatetimeSTR>28.01.2025 20:35:51</edatetimeSTR>
  </operation>
  <operation>
    <deviceID>T2058</deviceID>
    <userID>0907</userID>
    <sdatetimeSTR>29.01.2025 20:26:21</sdatetimeSTR>
    <edatetimeSTR>30.01.2025 8:56:13</edatetimeSTR>
  </operation>
  <operation>
    <deviceID>T2058</deviceID>
    <userID>2341</userID>
    <sdatetimeSTR>30.01.2025 20:57:43</sdatetimeSTR>
    <edatetimeSTR>31.01.2025 7:00:46</edatetimeSTR>
  </operation>
  <operation>
    <deviceID>T2058</deviceID>
    <userID>0365</userID>
    <sdatetimeSTR>01.02.2025 8:46:55</sdatetimeSTR>
    <edatetimeSTR>01.02.2025 12:27:54</edatetimeSTR>
  </operation>
  <operation>
    <deviceID>T2058</deviceID>
    <userID>3332</userID>
    <sdatetimeSTR>02.02.2025 15:23:01</sdatetimeSTR>
    <edatetimeSTR>02.02.2025 21:01:25</edatetimeSTR>
  </operation>
  <operation>
    <deviceID>T2058</deviceID>
    <userID>2682</userID>
    <sdatetimeSTR>03.02.2025 8:41:49</sdatetimeSTR>
    <edatetimeSTR>03.02.2025 20:57:59</edatetimeSTR>
  </operation>
  <operation>
    <deviceID>T2058</deviceID>
    <userID>3056</userID>
    <sdatetimeSTR>04.02.2025 8:30:48</sdatetimeSTR>
    <edatetimeSTR>04.02.2025 20:37:34</edatetimeSTR>
  </operation>
  <operation>
    <deviceID>T2058</deviceID>
    <userID>2557</userID>
    <sdatetimeSTR>06.02.2025 8:56:44</sdatetimeSTR>
    <edatetimeSTR>06.02.2025 16:09:18</edatetimeSTR>
  </operation>
  <operation>
    <deviceID>T2058</deviceID>
    <userID>3970</userID>
    <sdatetimeSTR>06.02.2025 20:31:40</sdatetimeSTR>
    <edatetimeSTR>07.02.2025 5:25:58</edatetimeSTR>
  </operation>
  <operation>
    <deviceID>T2058</deviceID>
    <userID>2048</userID>
    <sdatetimeSTR>07.02.2025 8:00:52</sdatetimeSTR>
    <edatetimeSTR>07.02.2025 8:34:24</edatetimeSTR>
  </operation>
  <operation>
    <deviceID>T2058</deviceID>
    <userID>3065</userID>
    <sdatetimeSTR>07.02.2025 20:48:55</sdatetimeSTR>
    <edatetimeSTR>08.02.2025 7:51:37</edatetimeSTR>
  </operation>
  <operation>
    <deviceID>T2058</deviceID>
    <userID>0123</userID>
    <sdatetimeSTR>08.02.2025 17:23:37</sdatetimeSTR>
    <edatetimeSTR>08.02.2025 21:08:48</edatetimeSTR>
  </operation>
  <operation>
    <deviceID>T2058</deviceID>
    <userID>3247</userID>
    <sdatetimeSTR>09.02.2025 8:16:03</sdatetimeSTR>
    <edatetimeSTR>09.02.2025 17:35:35</edatetimeSTR>
  </operation>
  <operation>
    <deviceID>T2058</deviceID>
    <userID>3115</userID>
    <sdatetimeSTR>10.02.2025 8:51:19</sdatetimeSTR>
    <edatetimeSTR>10.02.2025 18:04:45</edatetimeSTR>
  </operation>
  <operation>
    <deviceID>T2058</deviceID>
    <userID>3247</userID>
    <sdatetimeSTR>10.02.2025 20:30:31</sdatetimeSTR>
    <edatetimeSTR>11.02.2025 2:58:03</edatetimeSTR>
  </operation>
  <operation>
    <deviceID>T2058</deviceID>
    <userID>3028</userID>
    <sdatetimeSTR>11.02.2025 7:17:44</sdatetimeSTR>
    <edatetimeSTR>11.02.2025 8:54:55</edatetimeSTR>
  </operation>
  <operation>
    <deviceID>T2058</deviceID>
    <userID>1734</userID>
    <sdatetimeSTR>11.02.2025 20:51:57</sdatetimeSTR>
    <edatetimeSTR>12.02.2025 8:39:36</edatetimeSTR>
  </operation>
  <operation>
    <deviceID>T2058</deviceID>
    <userID>0558</userID>
    <sdatetimeSTR>12.02.2025 19:54:03</sdatetimeSTR>
    <edatetimeSTR>12.02.2025 20:55:27</edatetimeSTR>
  </operation>
  <operation>
    <deviceID>T2058</deviceID>
    <userID>3255</userID>
    <sdatetimeSTR>13.02.2025 9:01:26</sdatetimeSTR>
    <edatetimeSTR>13.02.2025 17:33:28</edatetimeSTR>
  </operation>
  <operation>
    <deviceID>T2058</deviceID>
    <userID>3141</userID>
    <sdatetimeSTR>13.02.2025 20:53:29</sdatetimeSTR>
    <edatetimeSTR>14.02.2025 5:33:43</edatetimeSTR>
  </operation>
  <operation>
    <deviceID>T2058</deviceID>
    <userID>3093</userID>
    <sdatetimeSTR>14.02.2025 7:35:23</sdatetimeSTR>
    <edatetimeSTR>14.02.2025 8:51:20</edatetimeSTR>
  </operation>
</operations>