<?xml version="1.0" encoding="utf-8"?>
<operations>
  <operation>
    <deviceID>
    </deviceID>
    <userID>0384</userID>
    <sdatetimeSTR>05.10.2022 20:50:05</sdatetimeSTR>
    <edatetimeSTR>06.10.2022 8:31:19</edatetimeSTR>
  </operation>
  <operation>
    <deviceID>
    </deviceID>
    <userID>2806</userID>
    <sdatetimeSTR>06.10.2022 20:26:48</sdatetimeSTR>
    <edatetimeSTR>07.10.2022 5:45:56</edatetimeSTR>
  </operation>
  <operation>
    <deviceID>
    </deviceID>
    <userID>1001</userID>
    <sdatetimeSTR>07.10.2022 20:52:22</sdatetimeSTR>
    <edatetimeSTR>08.10.2022 8:53:18</edatetimeSTR>
  </operation>
  <operation>
    <deviceID>
    </deviceID>
    <userID>1908</userID>
    <sdatetimeSTR>11.10.2022 20:57:25</sdatetimeSTR>
    <edatetimeSTR>12.10.2022 8:37:34</edatetimeSTR>
  </operation>
  <operation>
    <deviceID>
    </deviceID>
    <userID>1636</userID>
    <sdatetimeSTR>12.10.2022 20:30:01</sdatetimeSTR>
    <edatetimeSTR>13.10.2022 9:02:04</edatetimeSTR>
  </operation>
  <operation>
    <deviceID>
    </deviceID>
    <userID>2106</userID>
    <sdatetimeSTR>13.10.2022 20:47:50</sdatetimeSTR>
    <edatetimeSTR>14.10.2022 5:18:01</edatetimeSTR>
  </operation>
  <operation>
    <deviceID>
    </deviceID>
    <userID>2385</userID>
    <sdatetimeSTR>14.10.2022 8:26:20</sdatetimeSTR>
    <edatetimeSTR>14.10.2022 8:31:49</edatetimeSTR>
  </operation>
  <operation>
    <deviceID>
    </deviceID>
    <userID>1811</userID>
    <sdatetimeSTR>14.10.2022 20:49:03</sdatetimeSTR>
    <edatetimeSTR>15.10.2022 8:43:26</edatetimeSTR>
  </operation>
  <operation>
    <deviceID>
    </deviceID>
    <userID>2751</userID>
    <sdatetimeSTR>15.10.2022 20:43:26</sdatetimeSTR>
    <edatetimeSTR>16.10.2022 5:05:07</edatetimeSTR>
  </operation>
  <operation>
    <deviceID>
    </deviceID>
    <userID>0431</userID>
    <sdatetimeSTR>16.10.2022 8:43:33</sdatetimeSTR>
    <edatetimeSTR>16.10.2022 21:25:55</edatetimeSTR>
  </operation>
  <operation>
    <deviceID>
    </deviceID>
    <userID>1266</userID>
    <sdatetimeSTR>17.10.2022 9:11:08</sdatetimeSTR>
    <edatetimeSTR>17.10.2022 20:37:02</edatetimeSTR>
  </operation>
  <operation>
    <deviceID>
    </deviceID>
    <userID>0340</userID>
    <sdatetimeSTR>17.10.2022 20:40:22</sdatetimeSTR>
    <edatetimeSTR>18.10.2022 4:04:59</edatetimeSTR>
  </operation>
  <operation>
    <deviceID>
    </deviceID>
    <userID>0301</userID>
    <sdatetimeSTR>18.10.2022 4:14:13</sdatetimeSTR>
    <edatetimeSTR>18.10.2022 9:20:10</edatetimeSTR>
  </operation>
  <operation>
    <deviceID>
    </deviceID>
    <userID>2051</userID>
    <sdatetimeSTR>18.10.2022 20:35:24</sdatetimeSTR>
    <edatetimeSTR>19.10.2022 3:44:23</edatetimeSTR>
  </operation>
  <operation>
    <deviceID>
    </deviceID>
    <userID>1621</userID>
    <sdatetimeSTR>19.10.2022 8:53:22</sdatetimeSTR>
    <edatetimeSTR>19.10.2022 20:59:31</edatetimeSTR>
  </operation>
  <operation>
    <deviceID>
    </deviceID>
    <userID>2172</userID>
    <sdatetimeSTR>20.10.2022 9:01:18</sdatetimeSTR>
    <edatetimeSTR>20.10.2022 20:43:48</edatetimeSTR>
  </operation>
  <operation>
    <deviceID>
    </deviceID>
    <userID>1221</userID>
    <sdatetimeSTR>21.10.2022 8:38:05</sdatetimeSTR>
    <edatetimeSTR>21.10.2022 21:12:29</edatetimeSTR>
  </operation>
  <operation>
    <deviceID>
    </deviceID>
    <userID>1231</userID>
    <sdatetimeSTR>22.10.2022 20:31:08</sdatetimeSTR>
    <edatetimeSTR>23.10.2022 5:10:53</edatetimeSTR>
  </operation>
  <operation>
    <deviceID>
    </deviceID>
    <userID>2746</userID>
    <sdatetimeSTR>23.10.2022 20:35:28</sdatetimeSTR>
    <edatetimeSTR>24.10.2022 3:21:06</edatetimeSTR>
  </operation>
  <operation>
    <deviceID>
    </deviceID>
    <userID>0301</userID>
    <sdatetimeSTR>24.10.2022 8:48:50</sdatetimeSTR>
    <edatetimeSTR>24.10.2022 21:38:47</edatetimeSTR>
  </operation>
  <operation>
    <deviceID>
    </deviceID>
    <userID>2053</userID>
    <sdatetimeSTR>25.10.2022 9:02:09</sdatetimeSTR>
    <edatetimeSTR>25.10.2022 21:34:31</edatetimeSTR>
  </operation>
  <operation>
    <deviceID>
    </deviceID>
    <userID>1881</userID>
    <sdatetimeSTR>25.10.2022 22:41:27</sdatetimeSTR>
    <edatetimeSTR>26.10.2022 7:50:38</edatetimeSTR>
  </operation>
  <operation>
    <deviceID>
    </deviceID>
    <userID>2106</userID>
    <sdatetimeSTR>29.10.2022 20:36:37</sdatetimeSTR>
    <edatetimeSTR>30.10.2022 8:02:29</edatetimeSTR>
  </operation>
  <operation>
    <deviceID>
    </deviceID>
    <userID>1165</userID>
    <sdatetimeSTR>01.11.2022 8:55:16</sdatetimeSTR>
    <edatetimeSTR>01.11.2022 21:13:09</edatetimeSTR>
  </operation>
  <operation>
    <deviceID>
    </deviceID>
    <userID>1811</userID>
    <sdatetimeSTR>02.11.2022 8:46:49</sdatetimeSTR>
    <edatetimeSTR>02.11.2022 21:01:06</edatetimeSTR>
  </operation>
  <operation>
    <deviceID>
    </deviceID>
    <userID>2751</userID>
    <sdatetimeSTR>03.11.2022 9:04:03</sdatetimeSTR>
    <edatetimeSTR>03.11.2022 20:43:57</edatetimeSTR>
  </operation>
  <operation>
    <deviceID>
    </deviceID>
    <userID>2541</userID>
    <sdatetimeSTR>06.11.2022 17:14:18</sdatetimeSTR>
    <edatetimeSTR>06.11.2022 21:38:24</edatetimeSTR>
  </operation>
  <operation>
    <deviceID>
    </deviceID>
    <userID>0384</userID>
    <sdatetimeSTR>10.11.2022 20:52:25</sdatetimeSTR>
    <edatetimeSTR>11.11.2022 9:26:53</edatetimeSTR>
  </operation>
  <operation>
    <deviceID>
    </deviceID>
    <userID>2950</userID>
    <sdatetimeSTR>11.11.2022 9:26:54</sdatetimeSTR>
    <edatetimeSTR>11.11.2022 20:58:39</edatetimeSTR>
  </operation>
  <operation>
    <deviceID>
    </deviceID>
    <userID>1827</userID>
    <sdatetimeSTR>11.11.2022 21:07:55</sdatetimeSTR>
    <edatetimeSTR>11.11.2022 21:14:33</edatetimeSTR>
  </operation>
  <operation>
    <deviceID>
    </deviceID>
    <userID>0071</userID>
    <sdatetimeSTR>11.11.2022 21:18:05</sdatetimeSTR>
    <edatetimeSTR>12.11.2022 8:40:09</edatetimeSTR>
  </operation>
  <operation>
    <deviceID>
    </deviceID>
    <userID>2785</userID>
    <sdatetimeSTR>12.11.2022 20:41:45</sdatetimeSTR>
    <edatetimeSTR>16.11.2022 6:59:30</edatetimeSTR>
  </operation>
  <operation>
    <deviceID>
    </deviceID>
    <userID>2196</userID>
    <sdatetimeSTR>14.11.2022 20:47:18</sdatetimeSTR>
    <edatetimeSTR>16.11.2022 22:41:49</edatetimeSTR>
  </operation>
  <operation>
    <deviceID>
    </deviceID>
    <userID>1251</userID>
    <sdatetimeSTR>15.11.2022 20:50:49</sdatetimeSTR>
    <edatetimeSTR>19.11.2022 3:50:06</edatetimeSTR>
  </operation>
  <operation>
    <deviceID>
    </deviceID>
    <userID>1137</userID>
    <sdatetimeSTR>16.11.2022 21:18:11</sdatetimeSTR>
    <edatetimeSTR>24.11.2022 8:00:00</edatetimeSTR>
  </operation>
  <operation>
    <deviceID>
    </deviceID>
    <userID>2313</userID>
    <sdatetimeSTR>18.11.2022 20:59:25</sdatetimeSTR>
    <edatetimeSTR>25.11.2022 8:39:43</edatetimeSTR>
  </operation>
  <operation>
    <deviceID>
    </deviceID>
    <userID>1226</userID>
    <sdatetimeSTR>23.11.2022 20:32:19</sdatetimeSTR>
    <edatetimeSTR>26.11.2022 8:35:22</edatetimeSTR>
  </operation>
  <operation>
    <deviceID>
    </deviceID>
    <userID>2826</userID>
    <sdatetimeSTR>24.11.2022 20:49:06</sdatetimeSTR>
    <edatetimeSTR>26.11.2022 23:37:10</edatetimeSTR>
  </operation>
  <operation>
    <deviceID>
    </deviceID>
    <userID>0209</userID>
    <sdatetimeSTR>25.11.2022 20:53:05</sdatetimeSTR>
    <edatetimeSTR>27.11.2022 20:39:23</edatetimeSTR>
  </operation>
  <operation>
    <deviceID>
    </deviceID>
    <userID>2541</userID>
    <sdatetimeSTR>26.11.2022 13:40:55</sdatetimeSTR>
    <edatetimeSTR>29.11.2022 4:02:16</edatetimeSTR>
  </operation>
  <operation>
    <deviceID>
    </deviceID>
    <userID>2756</userID>
    <sdatetimeSTR>27.11.2022 8:35:42</sdatetimeSTR>
    <edatetimeSTR>01.12.2022 20:49:50</edatetimeSTR>
  </operation>
  <operation>
    <deviceID>
    </deviceID>
    <userID>1437</userID>
    <sdatetimeSTR>28.11.2022 20:33:55</sdatetimeSTR>
    <edatetimeSTR>02.12.2022 20:58:35</edatetimeSTR>
  </operation>
  <operation>
    <deviceID>
    </deviceID>
    <userID>2229</userID>
    <sdatetimeSTR>01.12.2022 8:55:38</sdatetimeSTR>
    <edatetimeSTR>03.12.2022 4:18:49</edatetimeSTR>
  </operation>
  <operation>
    <deviceID>
    </deviceID>
    <userID>1641</userID>
    <sdatetimeSTR>02.12.2022 8:28:10</sdatetimeSTR>
    <edatetimeSTR>04.12.2022 1:22:11</edatetimeSTR>
  </operation>
  <operation>
    <deviceID>
    </deviceID>
    <userID>2821</userID>
    <sdatetimeSTR>02.12.2022 21:02:00</sdatetimeSTR>
    <edatetimeSTR>04.12.2022 5:27:04</edatetimeSTR>
  </operation>
  <operation>
    <deviceID>
    </deviceID>
    <userID>1250</userID>
    <sdatetimeSTR>03.12.2022 8:40:21</sdatetimeSTR>
    <edatetimeSTR>04.12.2022 8:11:28</edatetimeSTR>
  </operation>
  <operation>
    <deviceID>
    </deviceID>
    <userID>1137</userID>
    <sdatetimeSTR>04.12.2022 1:22:12</sdatetimeSTR>
    <edatetimeSTR>04.12.2022 21:10:01</edatetimeSTR>
  </operation>
  <operation>
    <deviceID>
    </deviceID>
    <userID>1095</userID>
    <sdatetimeSTR>04.12.2022 8:11:22</sdatetimeSTR>
    <edatetimeSTR>05.12.2022 20:41:44</edatetimeSTR>
  </operation>
  <operation>
    <deviceID>
    </deviceID>
    <userID>2061</userID>
    <sdatetimeSTR>04.12.2022 8:33:28</sdatetimeSTR>
    <edatetimeSTR>06.12.2022 8:58:17</edatetimeSTR>
  </operation>
  <operation>
    <deviceID>
    </deviceID>
    <userID>2785</userID>
    <sdatetimeSTR>05.12.2022 8:42:41</sdatetimeSTR>
    <edatetimeSTR>07.12.2022 6:26:02</edatetimeSTR>
  </operation>
  <operation>
    <deviceID>
    </deviceID>
    <userID>2441</userID>
    <sdatetimeSTR>06.12.2022 0:08:07</sdatetimeSTR>
    <edatetimeSTR>07.12.2022 6:39:42</edatetimeSTR>
  </operation>
  <operation>
    <deviceID>
    </deviceID>
    <userID>2846</userID>
    <sdatetimeSTR>06.12.2022 20:18:13</sdatetimeSTR>
    <edatetimeSTR>07.12.2022 21:15:06</edatetimeSTR>
  </operation>
  <operation>
    <deviceID>
    </deviceID>
    <userID>0834</userID>
    <sdatetimeSTR>07.12.2022 6:38:39</sdatetimeSTR>
    <edatetimeSTR>08.12.2022 21:00:08</edatetimeSTR>
  </operation>
  <operation>
    <deviceID>
    </deviceID>
    <userID>2196</userID>
    <sdatetimeSTR>07.12.2022 9:09:51</sdatetimeSTR>
    <edatetimeSTR>09.12.2022 20:39:57</edatetimeSTR>
  </operation>
  <operation>
    <deviceID>
    </deviceID>
    <userID>1226</userID>
    <sdatetimeSTR>08.12.2022 8:27:15</sdatetimeSTR>
    <edatetimeSTR>10.12.2022 7:23:29</edatetimeSTR>
  </operation>
  <operation>
    <deviceID>
    </deviceID>
    <userID>0477</userID>
    <sdatetimeSTR>09.12.2022 8:44:17</sdatetimeSTR>
    <edatetimeSTR>11.12.2022 6:54:38</edatetimeSTR>
  </operation>
  <operation>
    <deviceID>
    </deviceID>
    <userID>1231</userID>
    <sdatetimeSTR>09.12.2022 20:40:47</sdatetimeSTR>
    <edatetimeSTR>12.12.2022 21:05:10</edatetimeSTR>
  </operation>
  <operation>
    <deviceID>
    </deviceID>
    <userID>2448</userID>
    <sdatetimeSTR>10.12.2022 20:42:05</sdatetimeSTR>
    <edatetimeSTR>14.12.2022 7:10:17</edatetimeSTR>
  </operation>
  <operation>
    <deviceID>
    </deviceID>
    <userID>2061</userID>
    <sdatetimeSTR>12.12.2022 9:30:07</sdatetimeSTR>
    <edatetimeSTR>14.12.2022 19:14:36</edatetimeSTR>
  </operation>
  <operation>
    <deviceID>
    </deviceID>
    <userID>1236</userID>
    <sdatetimeSTR>13.12.2022 20:53:31</sdatetimeSTR>
    <edatetimeSTR>16.12.2022 9:14:30</edatetimeSTR>
  </operation>
  <operation>
    <deviceID>
    </deviceID>
    <userID>0850</userID>
    <sdatetimeSTR>14.12.2022 13:06:29</sdatetimeSTR>
    <edatetimeSTR>16.12.2022 19:00:48</edatetimeSTR>
  </operation>
  <operation>
    <deviceID>
    </deviceID>
    <userID>0822</userID>
    <sdatetimeSTR>15.12.2022 20:44:49</sdatetimeSTR>
    <edatetimeSTR>17.12.2022 5:14:08</edatetimeSTR>
  </operation>
  <operation>
    <deviceID>TAB151</deviceID>
    <userID>2641</userID>
    <sdatetimeSTR>16.12.2022 19:00:24</sdatetimeSTR>
    <edatetimeSTR>26.12.2023 20:49:39</edatetimeSTR>
  </operation>
  <operation>
    <deviceID>TAB151</deviceID>
    <userID>0320</userID>
    <sdatetimeSTR>16.12.2022 20:21:43</sdatetimeSTR>
    <edatetimeSTR>26.12.2023 20:49:39</edatetimeSTR>
  </operation>
  <operation>
    <deviceID>TAB151</deviceID>
    <userID>1275</userID>
    <sdatetimeSTR>26.12.2023 9:46:05</sdatetimeSTR>
    <edatetimeSTR>26.12.2023 20:49:39</edatetimeSTR>
  </operation>
  <operation>
    <deviceID>TAB151</deviceID>
    <userID>2347</userID>
    <sdatetimeSTR>27.12.2023 20:14:54</sdatetimeSTR>
    <edatetimeSTR>28.12.2023 9:01:55</edatetimeSTR>
  </operation>
  <operation>
    <deviceID>TAB151</deviceID>
    <userID>2930</userID>
    <sdatetimeSTR>17.01.2024 11:25:53</sdatetimeSTR>
    <edatetimeSTR>17.01.2024 20:48:38</edatetimeSTR>
  </operation>
  <operation>
    <deviceID>TAB151</deviceID>
    <userID>2347</userID>
    <sdatetimeSTR>19.01.2024 9:19:29</sdatetimeSTR>
    <edatetimeSTR>20.01.2024 15:13:17</edatetimeSTR>
  </operation>
</operations>